setup.py
django_intercom_email_backend.egg-info/PKG-INFO
django_intercom_email_backend.egg-info/SOURCES.txt
django_intercom_email_backend.egg-info/dependency_links.txt
django_intercom_email_backend.egg-info/not-zip-safe
django_intercom_email_backend.egg-info/requires.txt
django_intercom_email_backend.egg-info/top_level.txt
intercom_email/__init__.py
intercom_email/backends.py