Metadata-Version: 1.0
Name: django-intercom-email-backend
Version: 0.9
Summary: Intercom email backend for Django
Home-page: https://github.com/cravefood/django-intercom-email-backend
Author: Sergio Oliveira
Author-email: seocam@seocam.com
License: UNKNOWN
Platform: UNKNOWN
